comments/__init__.py
comments/admin.py
comments/apps.py
comments/models.py
comments/tests.py
comments/views.py
comments/migrations/__init__.py
django_comments_app-0.1.0.dist-info/METADATA
django_comments_app-0.1.0.dist-info/WHEEL
django_comments_app-0.1.0.dist-info/top_level.txt
django_comments_app-0.1.0.dist-info/RECORD
